strong_augment/__init__.py
strong_augment/_augment.py
strong_augment/_shift.py
strong_augment-0.1.0.dist-info/WHEEL
strong_augment-0.1.0.dist-info/METADATA
strong_augment-0.1.0.dist-info/RECORD
