Metadata-Version: 2.1
Name: strong-augment
Version: 0.1.0
Summary: Augment like there's no tomorrow: Consistently performing neural networks
License: MIT
Author: jopo666
Author-email: jopo@birdlover.com
Requires-Python: >=3.9,<4.0
Classifier: License :: OSI Approved :: MIT License
Classifier: Programming Language :: Python :: 3
Classifier: Programming Language :: Python :: 3.9
Classifier: Programming Language :: Python :: 3.10
Classifier: Programming Language :: Python :: 3.11
Requires-Dist: numpy
Requires-Dist: opencv-python-headless (>=4.7,<5.0)
Requires-Dist: pillow (>=9,<10)
Requires-Dist: tqdm
